roboform/__init__.py
roboform/__main__.py
roboform/bot.py
roboform/cli.py
roboform/constants.py
roboform/form_configs.py
roboform/form_logs.py
roboform/global_configs.py
roboform/utils.py
roboform-1.0.3.dist-info/LICENSE
roboform-1.0.3.dist-info/METADATA
roboform-1.0.3.dist-info/WHEEL
roboform-1.0.3.dist-info/entry_points.txt
roboform-1.0.3.dist-info/top_level.txt
roboform-1.0.3.dist-info/RECORD
